fitsdataset/__init__.py
fitsdataset/dataset.py
fitsdataset-0.0.3.dist-info/LICENSE
fitsdataset-0.0.3.dist-info/METADATA
fitsdataset-0.0.3.dist-info/WHEEL
fitsdataset-0.0.3.dist-info/top_level.txt
fitsdataset-0.0.3.dist-info/RECORD
