Metadata-Version: 2.1
Name: fitsdataset
Version: 0.0.3
Summary: A PyTorch Dataset for the FITS file format
Home-page: https://github.com/amritrau/fitsdataset
Author: Amrit Rau
Requires-Python: >=3.6
License-File: LICENSE
Requires-Dist: numpy
Requires-Dist: pandas
Requires-Dist: torch
Requires-Dist: astropy
